odoo/addons/website_product_configurator/README.rst
odoo/addons/website_product_configurator/__init__.py
odoo/addons/website_product_configurator/__manifest__.py
odoo/addons/website_product_configurator/controllers/__init__.py
odoo/addons/website_product_configurator/controllers/main.py
odoo/addons/website_product_configurator/data/config_form_templates.xml
odoo/addons/website_product_configurator/data/cron.xml
odoo/addons/website_product_configurator/data/ir_config_parameter_data.xml
odoo/addons/website_product_configurator/demo/product_template_demo.xml
odoo/addons/website_product_configurator/i18n/de.po
odoo/addons/website_product_configurator/i18n/es.po
odoo/addons/website_product_configurator/i18n/es_VE.po
odoo/addons/website_product_configurator/i18n/it.po
odoo/addons/website_product_configurator/i18n/website_product_configurator.pot
odoo/addons/website_product_configurator/migrations/17.0.1.0.0/pre-migration.py
odoo/addons/website_product_configurator/models/__init__.py
odoo/addons/website_product_configurator/models/product_config.py
odoo/addons/website_product_configurator/models/res_config_settings.py
odoo/addons/website_product_configurator/models/sale_order.py
odoo/addons/website_product_configurator/readme/DESCRIPTION.md
odoo/addons/website_product_configurator/security/configurator_security.xml
odoo/addons/website_product_configurator/static/description/cover.png
odoo/addons/website_product_configurator/static/description/icon.png
odoo/addons/website_product_configurator/static/description/index.html
odoo/addons/website_product_configurator/static/src/js/config_form.esm.js
odoo/addons/website_product_configurator/static/src/js/website_sale.esm.js
odoo/addons/website_product_configurator/static/src/scss/config_form.scss
odoo/addons/website_product_configurator/static/src/scss/tooltip.scss
odoo/addons/website_product_configurator/static/tests/tours/website_config_tour.esm.js
odoo/addons/website_product_configurator/tests/__init__.py
odoo_addon_website_product_configurator-17.0.1.0.0.9.dist-info/METADATA
odoo_addon_website_product_configurator-17.0.1.0.0.9.dist-info/WHEEL
odoo_addon_website_product_configurator-17.0.1.0.0.9.dist-info/top_level.txt
odoo_addon_website_product_configurator-17.0.1.0.0.9.dist-info/RECORD
