Metadata-Version: 2.1
Name: odoo-addon-website_product_configurator
Version: 17.0.1.0.0.9
Requires-Python: >=3.10
Requires-Dist: odoo-addon-product_configurator>=17.0dev,<17.1dev
Requires-Dist: odoo-addon-product_configurator_sale>=17.0dev,<17.1dev
Requires-Dist: odoo>=17.0a,<17.1dev
Summary: Configure products in e-shop
Home-page: https://github.com/OCA/product-configurator
License: AGPL-3
Author: Pledra, Odoo Community Association (OCA)
Author-email: support@odoo-community.org
Classifier: Programming Language :: Python
Classifier: Framework :: Odoo
Classifier: Framework :: Odoo :: 17.0
Classifier: License :: OSI Approved :: GNU Affero General Public License v3
Classifier: Development Status :: 4 - Beta
